setup.py
date_data_cache/__init__.py
date_data_cache/cache.py
date_data_cache/cached_requests.py
date_data_cache/compress.py
date_data_cache/decorators.py
date_data_cache/generic_data.py
date_data_cache/persist_dict.py
persist_wrapper.egg-info/PKG-INFO
persist_wrapper.egg-info/SOURCES.txt
persist_wrapper.egg-info/dependency_links.txt
persist_wrapper.egg-info/top_level.txt