Metadata-Version: 1.1
Name: persist-wrapper
Version: 0.0.60
Summary: Utility to cache date-based data
Home-page: https://github.com/jayalane/persist_wrapper
Author: Chris Lane
Author-email: chris@lane-jayasinha.com
License: BSD
Platform: UNKNOWN
Classifier: Development Status :: 3 - Alpha
Classifier: License :: OSI Approved :: BSD License
